Workbook

Sheet Supuestos
B2: MESA MAKLO — Modelo de los 3 numeros
B3: Cierra la tarea ALTA del red-team (PREP_Mesa_MAKLO_interno.md §1). USO INTERNO — no se presenta.
B4: LEGENDA: celdas AMARILLAS = tu dato, reemplazalas. Azul = input. Negro = formula (no tocar).
B6: 1 · TU COSTO (lo unico que fija el PISO) | C6: Valor | D6: Unidad | E6: De donde sale / nota
B7: Tu tarifa-hora objetivo | C7: 35 | D7: $/hora | E7: HIPOTESIS. Tu costo de oportunidad real por hora dedicada.
B8: Costo infra mensual asignable al proyecto | C8: 40 | D8: $/mes | E8: HIPOTESIS. Hosting+DB+dominio+storage atribuible.
B9: Costo de inferencia por conversacion | C9: 0.12 | D9: $/conv | E9: HIPOTESIS. MEDIBLE con precision (API por tokens). Medilo antes de la mesa.
B10: COGS WhatsApp por conversacion | C10: 0.08 | D10: $/conv | E10: HIPOTESIS. Meta cobra conversaciones respondidas desde 01-10-2026 (tesis Senales-Brain).
B12: 2 · MONTAJE (setup, una sola vez) | C12: Valor | D12: Unidad | E12: De donde sale / nota
B13: Horas de montaje del storefront (a mano) | C13: 40 | D13: horas | E13: Modulo A. Plantilla parametrizada + carga del proyecto.
B14: Unidades del proyecto | C14: 20 | D14: unidades | E14: Confirmar en la mesa (checklist §6). Afecta carga de fichas.
B15: Horas de carga/ficha por unidad | C15: 0.5 | D15: h/unidad | E15: Specs por unidad en tabla estructurada (sin RAG, ~20 unidades).
B16: Horas de verificacion en terreno (eje La Concepcion) | C16: 16 | D16: horas | E16: Modulo A. Isocronas peatonales reales + POIs + sello y fecha.
B17: Transporte / logistica de verificacion | C17: 60 | D17: $ | E17: HIPOTESIS. Movilidad para la verificacion en terreno.
B18: Horas de entrenamiento del agente para el proyecto | C18: 12 | D18: horas | E18: Modulo B. Flujo de calificacion + guardrails + specs.
B19: Produccion de QR / valla | C19: 50 | D19: $ | E19: HIPOTESIS. Confirmar si lo cubre MAKLO.
B21: 3 · OPERACION (mensual, durante el mandato) | C21: Valor | D21: Unidad | E21: De donde sale / nota
B22: Conversaciones estimadas por mes | C22: 250 | D22: conv/mes | E22: HIPOTESIS CRITICA. Escala el costo variable. Calibrar con pauta real.
B23: Horas/mes de operacion de campana | C23: 10 | D23: horas/mes | E23: Modulo C. Diseno + operacion + optimizacion de pauta.
B24: Horas/mes de reporte semanal | C24: 4 | D24: horas/mes | E24: Modulo E. 4 reportes/mes, ~1h c/u.
B25: Horas/mes de re-verificacion periodica | C25: 3 | D25: horas/mes | E25: Fase 2: 'un sello viejo es peor que ninguno'.
B26: Horas/mes de soporte y coordinacion | C26: 4 | D26: horas/mes | E26: Atencion al cliente, ajustes, reuniones.
B28: 4 · MARGEN Y PLAZO (tus palancas de negociacion) | C28: Valor | D28: Unidad | E28: De donde sale / nota
B29: Margen MINIMO aceptable (define el PISO) | C29: 0.2 | D29: % | E29: Por debajo trabajas a perdida. Innegociable.
B30: Margen TARGET (socio fundador del carril) | C30: 0.6 | D30: % | E30: Honesto pero no regalado. Es tu ancla de apertura.
B31: Plazo del mandato | C31: 9 | D31: meses | E31: Exclusiva por plazo definido (propuesta §8).
B32: Descuento socio fundador vs tarifa futura | C32: 0.3 | D32: % | E32: Lo que reconoces por ser el primer edificio (propuesta §6).
B34: ⚠ Ninguna cifra de arriba es un dato medido. Son HIPOTESIS de arranque: reemplazalas con tus
B35: numeros reales antes del miercoles. El unico medible con precision HOY: el costo de inferencia.

Sheet Costo de servir
B2: COSTO DE SERVIR — MAKLO
B3: Formula heredada de pricing-detalle.md §4.1: Fijo + Variable_por_lead x N + Soporte
B5: A · MONTAJE (una sola vez) | C5: USD | D5: Composicion
B6: Montaje del storefront | C6: =Supuestos!C13*Supuestos!C7 | D6: horas montaje x tarifa-hora
B7: Carga de fichas por unidad | C7: =Supuestos!C14*Supuestos!C15*Supuestos!C7 | D7: unidades x h/unidad x tarifa-hora
B8: Verificacion en terreno | C8: =Supuestos!C16*Supuestos!C7 | D8: horas verificacion x tarifa-hora
B9: Transporte / logistica | C9: =Supuestos!C17 | D9: gasto directo
B10: Entrenamiento del agente | C10: =Supuestos!C18*Supuestos!C7 | D10: horas entrenamiento x tarifa-hora
B11: QR / valla | C11: =Supuestos!C19 | D11: gasto directo
B12: COSTO TOTAL DE MONTAJE | C12: =SUM(C6:C11) | D12: Tu PISO del setup (antes de margen)
B14: B · OPERACION (por mes) | C14: USD | D14: Composicion
B15: Inferencia del agente | C15: =Supuestos!C22*Supuestos!C9 | D15: conversaciones/mes x costo por conversacion
B16: COGS WhatsApp | C16: =Supuestos!C22*Supuestos!C10 | D16: conversaciones/mes x costo Meta (desde oct-2026)
B17: Infra asignable | C17: =Supuestos!C8 | D17: hosting + DB + dominio
B18: Operacion de campana | C18: =Supuestos!C23*Supuestos!C7 | D18: horas/mes x tarifa-hora
B19: Reporte semanal | C19: =Supuestos!C24*Supuestos!C7 | D19: horas/mes x tarifa-hora
B20: Re-verificacion periodica | C20: =Supuestos!C25*Supuestos!C7 | D20: horas/mes x tarifa-hora
B21: Soporte y coordinacion | C21: =Supuestos!C26*Supuestos!C7 | D21: horas/mes x tarifa-hora
B22: COSTO TOTAL MENSUAL | C22: =SUM(C15:C21) | D22: Tu PISO del mensual (antes de margen)
B24: C · TOTAL DEL MANDATO | C24: USD | D24: Composicion
B25: Horas totales comprometidas (montaje) | C25: =Supuestos!C13+Supuestos!C14*Supuestos!C15+Supuestos!C16+Supuestos!C18 | D25: suma de horas one-time
B26: Horas totales comprometidas (operacion) | C26: =(Supuestos!C23+Supuestos!C24+Supuestos!C25+Supuestos!C26)*Supuestos!C31 | D26: horas/mes x plazo
B27: COSTO TOTAL DEL MANDATO | C27: =C12+C22*Supuestos!C31 | D27: montaje + (mensual x plazo)
B29: Verificacion de realidad: ¿esas horas totales caben en tu semana junto al piloto PYME y el CRM?
B30: Riesgo #3 del PREP (CAPACIDAD): si MAKLO pasa al frente es una DECISION registrada, no inercia.

Sheet Los 3 numeros
B2: LOS 3 NUMEROS — llevalos MEMORIZADOS a la mesa
B3: Regla de mesa #2: cero montos en el doc presentable. El ancla la ponemos NOSOTROS, verbalmente.
B5: Escenario | C5: Setup (una vez) | D5: Mensual | E5: Cuando se usa / que protege
B6: COSTO (sin margen) | C6: ='Costo de servir'!C12 | D6: ='Costo de servir'!C22 | E6: Lo que te cuesta servir. Nunca se dice en voz alta.
B7: 🔴 WALK-AWAY | C7: ='Costo de servir'!C12 | D7: ='Costo de servir'!C22 | E7: Por debajo trabajas gratis o a perdida. Te levantas de la mesa.
B8: 🟡 PISO (minimo aceptable) | C8: ='Costo de servir'!C12*(1+Supuestos!C29) | D8: ='Costo de servir'!C22*(1+Supuestos!C29) | E8: Tu ultimo movimiento. No se baja de aqui bajo ninguna presion.
B9: 🟢 TARGET (socio fundador) | C9: ='Costo de servir'!C12*(1+Supuestos!C30) | D9: ='Costo de servir'!C22*(1+Supuestos!C30) | E9: TU ANCLA DE APERTURA. El primer numero que decis en la mesa.
B10: Tarifa futura (no-fundador) | C10: =C9/(1-Supuestos!C32) | D10: =D9/(1-Supuestos!C32) | E10: Lo que costara al 2do cliente. Hace VISIBLE el descuento de socio fundador.
B12: VALOR TOTAL DEL MANDATO (para tu cabeza, no para la mesa)
B13: Escenario | C13: Ingreso total | D13: Margen $ | E13: Lectura
B14: Si cierra en PISO | C14: =C8+D8*Supuestos!C31 | D14: =C14-'Costo de servir'!C27 | E14: Sobrevivis. No crecas.
B15: Si cierra en TARGET | C15: =C9+D9*Supuestos!C31 | D15: =C15-'Costo de servir'!C27 | E15: El carril arranca sano.
B17: Ingreso total = setup + (mensual x plazo). El componente variable (fee por visita calificada
B18: confirmada) NO esta modelado: es palanca de negociacion, no base de ingreso.
B20: LAS 4 CONDICIONES DE WALK-AWAY (no son numeros)
B21: 1. Condicionan el mandato a que invirtamos | C21: Regla escrita §2 del PREP. Mesas separadas, sin excepcion. 🔴
B22: 2. Exigen % de venta o 'cobrame solo si vendes' | C22: Nos vuelve el intermediario que ELLOS decidieron eliminar. 🔴
B23: 3. Piden ranking preferente en la app de Contexto | C23: Rompe la neutralidad = rompe el activo. 🔴
B24: 4. Sin presupuesto de pauta sostenible | C24: Regla de mesa #3: sin presupuesto de demanda no hay mandato. 🔴

Sheet Ancla de valor (mesa)
B2: ANCLA DE VALOR — se llena EN la mesa (primera parte, 80/20)
B3: PREP §1: el benchmark NO es el 3-4% de la comercializadora (ese ya se lo regalaron al comprador).
B4: Es lo que les costo vender el proyecto 1 ELLOS MISMOS. Su evidencia, no nuestra opinion.
B6: Pregunta (en sus palabras) | C6: Respuesta | D6: Por que importa
B7: ¿Cuantas unidades tuvo el proyecto 1? | D7: Base de comparacion.
B8: ¿Cuanto tardaron en venderlo todo? (meses) | D8: El costo del tiempo es el ancla real.
B9: ¿Quien vendia? ¿cuantas horas/semana le metian? | D9: Convierte su dolor en horas medibles.
B10: ¿Que gastaron en pauta/marketing en total? | D10: Su baseline de inversion en demanda.
B11: ¿Tienen lista de interesados que no compraron? | D11: REACTIVACION ~$0 — la pregunta #1 del playbook.
B12: ¿Cuanto costo el credito puente por cada mes extra? | D12: El costo financiero de vender lento (suelen olvidarlo).
B13: ¿Presupuesto de pauta mensual sostenible? | D13: Sin esto NO hay mandato (regla de mesa #3).
B14: ¿Precio por unidad y beneficio al comprador (%)? | D14: Define la campana y si los precios son realistas.
B17: EL CALCULO QUE HACES EN VIVO
B18: Meses de venta lenta x costo mensual del proyecto (credito puente + admin + su tiempo)
B19: =lo que les costo NO tener una maquina. Ese numero compara contra tu fee.
B21: Si ese numero es MUCHO mayor que tu target (lo normal), no defendes precio: defendes ahorro.
B22: Si es menor, el proyecto no aguanta el servicio — mejor saberlo en la mesa que en el mes 3.
